{"name":"Valid login","id":"login;valid-login","scenarioId":"classpath:features/login:Valid login","methodName":"Valid login","testSteps":[{"number":1,"description":"Given the user navigates to the login page","duration":0,"startTime":"2025-05-14T18:37:55.239716200Z[Etc/UTC]","result":"SUCCESS","precondition":false,"level":0},{"number":2,"description":"When they enter username \"tomsmith\" and password \"SuperSecretPassword!\"","duration":0,"startTime":"2025-05-14T18:37:55.241134671Z[Etc/UTC]","result":"SUCCESS","precondition":false,"level":0},{"number":3,"description":"Then they should see the message \"You logged into a secure area!\"","duration":0,"startTime":"2025-05-14T18:37:55.241323734Z[Etc/UTC]","result":"SUCCESS","precondition":false,"level":0}],"userStory":{"id":"classpath:features/login","storyName":"Login","displayName":"Login","path":"login","pathElements":[{"name":"login","description":""}],"type":"feature"},"title":"Valid login","description":"","tags":[{"name":"Linux","type":"context","displayName":"Linux"}],"startTime":"2025-05-14T18:37:36.381145420Z[Etc/UTC]","duration":18533,"projectKey":"","isManualTestingUpToDate":false,"context":"linux","manual":false,"testSource":"Cucumber","result":"SUCCESS"}